<!-- Signals.xml : auto generated (Mon Mar 17 00:10:17 2025) -->
   <signal name="InternalSignal"/>
   <signal name="InternalTaskSignal"/>
   <signal name="InternalDationSignal"/>
   <signal name="InternalDatatypeSignal"/>
   <signal name="InternalConfigurationSignal"/>
   <signal name="TerminateRequestSignal"/>
   <signal name="ArithmeticOverflowSignal"/>
   <signal name="ArithmeticUnderflowSignal"/>
   <signal name="ArithmeticDivideByZeroSignal"/>
   <signal name="InternalSignalsSignal"/>
   <signal name="AnySignal"/>
   <signal name="TaskSignal"/>
   <signal name="PrioOutOfRangeSignal"/>
   <signal name="TaskRunningSignal"/>
   <signal name="TaskSuspendedSignal"/>
   <signal name="TaskTerminatedSignal"/>
   <signal name="IllegalSchedulingSignal"/>
   <signal name="SemaOverflowSignal"/>
   <signal name="BoltStateSignal"/>
   <signal name="BoltReserveDuplicateSignal"/>
   <signal name="DataValueSignal"/>
   <signal name="FixedRangeSignal"/>
   <signal name="FixedDivideByZeroSignal"/>
   <signal name="DurationDivideByZeroSignal"/>
   <signal name="DurationRangeSignal"/>
   <signal name="FloatIsNaNSignal"/>
   <signal name="FloatIsINFSignal"/>
   <signal name="FunctionParameterOutOfRangeException"/>
   <signal name="BitIndexOutOfRangeSignal"/>
   <signal name="CharacterTooLongSignal"/>
   <signal name="CharacterIndexOutOfRangeSignal"/>
   <signal name="CharIsINVSignal"/>
   <signal name="ArrayIndexOutOfBoundsSignal"/>
   <signal name="RefNotInitializedSignal"/>
   <signal name="BadArraySegmentSignal"/>
   <signal name="DationSignal"/>
   <signal name="DationParamSignal"/>
   <signal name="DationNotOpenSignal"/>
   <signal name="OpenFailedSignal"/>
   <signal name="CloseFailedSignal"/>
   <signal name="PositioningFailedSignal"/>
   <signal name="InvalidPositioningSignal"/>
   <signal name="ReadingFailedSignal"/>
   <signal name="WritingFailedSignal"/>
   <signal name="DationIndexBoundSignal"/>
   <signal name="DationNotSupportedSignal"/>
   <signal name="DationEOFSignal"/>
   <signal name="NoEOFDationSignal"/>
   <signal name="DationTFURecordSignal"/>
   <signal name="DationDatatypeSignal"/>
   <signal name="DationFormatRepetitionValue"/>
   <signal name="DationFormatRepetitionOverflow"/>
   <signal name="DeviceNotFoundSignal"/>
   <signal name="FormatSignal"/>
   <signal name="NoMoreCharactersSignal"/>
   <signal name="DurationFormatSignal"/>
   <signal name="ClockFormatSignal"/>
   <signal name="FixedFormatSignal"/>
   <signal name="CharacterFormatSignal"/>
   <signal name="BitFormatSignal"/>
   <signal name="ClockValueSignal"/>
   <signal name="FixedValueSignal"/>
   <signal name="BitValueSignal"/>
   <signal name="DurationValueSignal"/>
   <signal name="ExpFormatSignal"/>
   <signal name="ExpValueSignal"/>
